cs/buffer.py
cs_buffer-20250428.dist-info/WHEEL
cs_buffer-20250428.dist-info/METADATA
cs_buffer-20250428.dist-info/RECORD
